<?xml version='1.0' encoding='utf-8'?>
<song xmlns="http://openlyrics.info/namespace/2009/song" version="0.8" createdIn="OpenLP 2.0.1" modifiedIn="OpenLP 2.0.1" modifiedDate="2013-09-13T00:34:24">
  <properties>
    <titles>
      <title>Let everything that has breath (Unformatted)</title>
    </titles>
    <verseOrder>c1 v1 p1 c1 v2 p1 c1</verseOrder>
    <authors>
      <author>Unknown</author>
    </authors>
  </properties>
  <lyrics>
    <verse name="v1">
      <lines>Praise You in the morning,<br/>Praise You in the evening,<br/>Praise You when I'm young and when I'm old.<br/>Praise You when I'm laughing,<br/>Praise You when I'm grieving,<br/>Praise You every season of the soul.</lines>
    </verse>
    <verse name="p1">
      <lines>If we could see how much You're worth,<br/>Your power, Your might, Your endless love,<br/>Then surely we would never cease to praise.</lines>
    </verse>
    <verse name="c1">
      <lines>Let everything that, everything that,<br/>Everything that has breath praise the Lord.<br/>Let everything that, everything that,<br/>Everything that has breath praise the Lord.</lines>
    </verse>
    <verse name="v2">
      <lines>Praise You in the heavens, <br/>Joining with the angels,<br/>Praising You forever and a day.<br/>Praise You on the earth now, <br/>Joining with creation,<br/>Calling all the nations to Your praise.</lines>
    </verse>
  </lyrics>
</song>
